{
  "title": "Apprentissage",
  "school":
  {
    "title":"Cursus scolaire",
    "content": [
      {
        "title": "Diplôme Chef de projet web",
        "name": "FIM CCI Formation Saint-Lô",
        "year": "2024-2025",
        "certif": "En cours"
      },
      {
        "title": "Diplôme Webdesigner",
        "name": "FIM CCI Formation Saint-Lô",
        "year": "2024-2025",
        "certif": "obtenu"
      },
      {
        "title": "BAC Professionnel Réseau Informatique & Système Communicant",
        "name": "Lycée Curie Corot Saint-Lô (2021) / Lycée Charles Tellier Condé-sur-Noireau",
        "year": "2021-2023",
        "certif": "obtenu"
      }
    ]
  },

  "personal":
  {
    "title":"Apprentissage personnel",
    "content": [
      {
        "title": "OpenClassrooms"
      },
      {
        "title": "Codédex"
      },
      {
        "title": "Roadmap.sh"
      }
    ]
  }
}